scm_cli/__init__.py
scm_cli/client.py
scm_cli/commands/README.md
scm_cli/commands/__init__.py
scm_cli/commands/command-styling.md
scm_cli/commands/context.py
scm_cli/commands/deployment.py
scm_cli/commands/insights.py
scm_cli/commands/network.py
scm_cli/commands/objects.py
scm_cli/commands/security.py
scm_cli/main.py
scm_cli/tests/__init__.py
scm_cli/utils/__init__.py
scm_cli/utils/config.py
scm_cli/utils/context.py
scm_cli/utils/sdk_client.py
scm_cli/utils/validators.py
pan_scm_cli-0.5.2.dist-info/LICENSE
pan_scm_cli-0.5.2.dist-info/METADATA
pan_scm_cli-0.5.2.dist-info/WHEEL
pan_scm_cli-0.5.2.dist-info/entry_points.txt
pan_scm_cli-0.5.2.dist-info/RECORD
