Metadata-Version: 2.3
Name: pan-scm-cli
Version: 0.5.2
Summary: CICD and Network Engineer-friendly CLI tool for Palo Alto Networks Strata Cloud Manager
Author: Calvin Remsburg
Author-email: dev@cdot.io
Requires-Python: >=3.12,<3.14
Classifier: Programming Language :: Python :: 3
Classifier: Programming Language :: Python :: 3.12
Classifier: Programming Language :: Python :: 3.13
Requires-Dist: dynaconf (>=3.2.11,<4.0.0)
Requires-Dist: pan-scm-sdk (==0.3.42)
Requires-Dist: pydantic (>=2.11.5,<3.0.0)
Requires-Dist: pyyaml (>=6.0.2,<7.0.0)
Requires-Dist: typer (>=0.15.4,<0.16.0)
